{
  "routes": [
    {
      "method": "GET",
      "path": "/info-sections",
      "handler": "info-section.find",
      "config": {
        "policies": []
      }
    },
    {
      "method": "GET",
      "path": "/info-sections/count",
      "handler": "info-section.count",
      "config": {
        "policies": []
      }
    },
    {
      "method": "GET",
      "path": "/info-sections/:id",
      "handler": "info-section.findOne",
      "config": {
        "policies": []
      }
    },
    {
      "method": "POST",
      "path": "/info-sections",
      "handler": "info-section.create",
      "config": {
        "policies": []
      }
    },
    {
      "method": "PUT",
      "path": "/info-sections/:id",
      "handler": "info-section.update",
      "config": {
        "policies": []
      }
    },
    {
      "method": "DELETE",
      "path": "/info-sections/:id",
      "handler": "info-section.delete",
      "config": {
        "policies": []
      }
    }
  ]
}
